zanna
