Metadata-Version: 1.1
Name: zanna
Version: 0.3.1
Summary: Simple Dependency Injection library
Home-page: https://github.com/MirkoRossini/zanna
Author: Mirko Rossini
Author-email: mirko.rossini@ymail.com
License: BSD license
Keywords: zanna
Platform: UNKNOWN
Classifier: Development Status :: 2 - Pre-Alpha
Classifier: Intended Audience :: Developers
Classifier: License :: OSI Approved :: BSD License
Classifier: Natural Language :: English
Classifier: Programming Language :: Python :: 2
Classifier: Programming Language :: Python :: 2.6
Classifier: Programming Language :: Python :: 2.7
Classifier: Programming Language :: Python :: 3
Classifier: Programming Language :: Python :: 3.3
Classifier: Programming Language :: Python :: 3.4
Classifier: Programming Language :: Python :: 3.5
